quantity/__init__.py
quantity/converter.py
quantity/exceptions.py
quantity/predefined.py
quantity/qtybase.py
quantity/term.py
quantity/version.py
quantity/money/__init__.py
quantity/money/converter.py
quantity/money/currencies.py
quantity/money/iso_4217.xml
quantity/money/moneybase.py
quantity-0.10.1.dist-info/LICENCE.txt
quantity-0.10.1.dist-info/METADATA
quantity-0.10.1.dist-info/WHEEL
quantity-0.10.1.dist-info/top_level.txt
quantity-0.10.1.dist-info/RECORD
