Metadata-Version: 2.1
Name: quantity
Version: 0.10.1
Summary: Unit-safe computations with quantities (including money)
Home-page: https://github.com/mamrhein/quantity
Author: Michael Amrhein
Author-email: michael@adrhinum.de
License: BSD
Keywords: quantity quantities unit units money currency exchange
Platform: all
Classifier: Development Status :: 4 - Beta
Classifier: Intended Audience :: Developers
Classifier: License :: OSI Approved :: BSD License
Classifier: Operating System :: OS Independent
Classifier: Programming Language :: Python
Classifier: Programming Language :: Python :: 3
Classifier: Programming Language :: Python :: 3.6
Classifier: Programming Language :: Python :: 3.7
Classifier: Programming Language :: Python :: 3.8
Classifier: Programming Language :: Python :: 3.9
Classifier: Programming Language :: Python :: Implementation :: CPython
Classifier: Programming Language :: Python :: Implementation :: PyPy
Classifier: Topic :: Software Development
Classifier: Topic :: Software Development :: Libraries
Classifier: Topic :: Software Development :: Libraries :: Python Modules
Requires-Python: >=3.6
Requires-Dist: decimalfp (>=0.11.1)
